bareasgi_prometheus/__init__.py
bareasgi_prometheus/helpers.py
bareasgi_prometheus/metrics/__init__.py
bareasgi_prometheus/metrics/http_request_metric.py
bareasgi_prometheus/metrics/prometheus_http_request_metric.py
bareasgi_prometheus/middleware.py
bareasgi_prometheus/py.typed
bareasgi_prometheus/view.py
bareasgi_prometheus-4.2.0.dist-info/LICENSE
bareasgi_prometheus-4.2.0.dist-info/WHEEL
bareasgi_prometheus-4.2.0.dist-info/METADATA
bareasgi_prometheus-4.2.0.dist-info/RECORD
