Metadata-Version: 2.1
Name: bareasgi-prometheus
Version: 4.2.0
Summary: Prometheus metrics for bareASGI
Home-page: https://github.com/rob-blackbourn/bareASGI-prometheus
License: Apache-2.0
Author: Rob Blackbourn
Author-email: rob.blackbourn@gmail.com
Requires-Python: >=3.8,<4.0
Classifier: License :: OSI Approved :: Apache Software License
Classifier: Programming Language :: Python :: 3
Classifier: Programming Language :: Python :: 3.10
Classifier: Programming Language :: Python :: 3.8
Classifier: Programming Language :: Python :: 3.9
Requires-Dist: bareASGI (>=4.0.0,<5.0.0)
Requires-Dist: jetblack-metrics (>=1,<2)
Requires-Dist: prometheus_client (>=0.13,<0.14)
Project-URL: Repository, https://github.com/rob-blackbourn/bareASGI-prometheus
